routeros_api_fork/__init__.py
routeros_api_fork/api.py
routeros_api_fork/api_socket.py
routeros_api_fork/api_structure.py
routeros_api_fork/base_api.py
routeros_api_fork/communication_exception_parsers.py
routeros_api_fork/exceptions.py
routeros_api_fork/query.py
routeros_api_fork/resource.py
routeros_api_fork/sentence.py
routeros_api_fork/utils.py
routeros_api_fork/api_communicator/__init__.py
routeros_api_fork/api_communicator/async_decorator.py
routeros_api_fork/api_communicator/base.py
routeros_api_fork/api_communicator/encoding_decorator.py
routeros_api_fork/api_communicator/exception_decorator.py
routeros_api_fork/api_communicator/key_cleaner_decorator.py
routeros_api_fork-0.19.0.dist-info/METADATA
routeros_api_fork-0.19.0.dist-info/WHEEL
routeros_api_fork-0.19.0.dist-info/licenses/LICENSE
routeros_api_fork-0.19.0.dist-info/RECORD
