Metadata-Version: 2.3
Name: routeros-api-fork
Version: 0.19.0
Summary: Python API to RouterBoard devices produced by MikroTik.
Project-URL: Homepage, https://github.com/xoste49/RouterOS-api-fork
Author-email: Pavel Korchagin <xoste49@gmail.com>, Social WiFi <it@socialwifi.com>
License: MIT
License-File: LICENSE
Keywords: API,MikroTik,RouterOS
Requires-Python: >=3.9
Requires-Dist: chardet>=5.2.0
